bgsolver/56k_valid_words.txt
bgsolver/__init__.py
bgsolver/board.py
bgsolver/main.py
bgsolver/player.py
bgsolver/word.py
bgsolver-0.1.dist-info/LICENSE
bgsolver-0.1.dist-info/METADATA
bgsolver-0.1.dist-info/WHEEL
bgsolver-0.1.dist-info/entry_points.txt
bgsolver-0.1.dist-info/RECORD
